Metadata-Version: 2.1
Name: pygameoflife-dadeerh
Version: 1.1.6
Summary: Pygame implementation of Conway's Game of Life
Home-page: https://github.com/Dadeerh/pygameoflife_dadeerh
Author: dadeerh
Author-email: dadeerh91@gmail.com
License: GPL-3.0
Platform: UNKNOWN
